masque/LICENSE.md
masque/README.md
masque/__init__.py
masque/abstract.py
masque/error.py
masque/label.py
masque/library.py
masque/pattern.py
masque/ports.py
masque/py.typed
masque/ref.py
masque/repetition.py
masque/builder/__init__.py
masque/builder/builder.py
masque/builder/pather.py
masque/builder/renderpather.py
masque/builder/tools.py
masque/builder/utils.py
masque/file/__init__.py
masque/file/dxf.py
masque/file/gdsii.py
masque/file/oasis.py
masque/file/svg.py
masque/file/utils.py
masque/shapes/__init__.py
masque/shapes/arc.py
masque/shapes/circle.py
masque/shapes/ellipse.py
masque/shapes/path.py
masque/shapes/polygon.py
masque/shapes/shape.py
masque/shapes/text.py
masque/test/__init__.py
masque/test/conftest.py
masque/test/test_fdfd.py
masque/traits/__init__.py
masque/traits/annotatable.py
masque/traits/copyable.py
masque/traits/layerable.py
masque/traits/mirrorable.py
masque/traits/positionable.py
masque/traits/repeatable.py
masque/traits/rotatable.py
masque/traits/scalable.py
masque/utils/__init__.py
masque/utils/array.py
masque/utils/autoslots.py
masque/utils/bitwise.py
masque/utils/comparisons.py
masque/utils/curves.py
masque/utils/decorators.py
masque/utils/deferreddict.py
masque/utils/pack2d.py
masque/utils/ports2data.py
masque/utils/transform.py
masque/utils/types.py
masque/utils/vertices.py
masque-3.4.dist-info/METADATA
masque-3.4.dist-info/WHEEL
masque-3.4.dist-info/licenses/LICENSE.md
masque-3.4.dist-info/RECORD
