Metadata-Version: 2.4
Name: masque
Version: 3.4
Summary: Lithography mask library
Author-email: Jan Petykiewicz <jan@mpxd.net>
License: GNU Affero General Public License
License-File: LICENSE.md
Keywords: CAD,EDA,OASIS,dxf,gds,gds2,gdsii,layout,lithography,mask,oas,pattern,stream,svg
Classifier: Development Status :: 4 - Beta
Classifier: Intended Audience :: Developers
Classifier: Intended Audience :: Information Technology
Classifier: Intended Audience :: Manufacturing
Classifier: Intended Audience :: Science/Research
Classifier: License :: OSI Approved :: GNU Affero General Public License v3
Classifier: Programming Language :: Python :: 3
Classifier: Topic :: Scientific/Engineering :: Electronic Design Automation (EDA)
Classifier: Topic :: Scientific/Engineering :: Visualization
Requires-Python: >=3.11
Requires-Dist: klamath~=1.4
Requires-Dist: numpy>=1.26
Provides-Extra: dxf
Requires-Dist: ezdxf~=1.0.2; extra == 'dxf'
Provides-Extra: oasis
Requires-Dist: fatamorgana~=0.11; extra == 'oasis'
Provides-Extra: svg
Requires-Dist: svgwrite; extra == 'svg'
Provides-Extra: text
Requires-Dist: freetype-py; extra == 'text'
Requires-Dist: matplotlib; extra == 'text'
Provides-Extra: visualize
Requires-Dist: matplotlib; extra == 'visualize'
